odoo10_addon_webhook-10.0.1.0.0-py2.7-nspkg.pth
odoo/addons/webhook/README.rst
odoo/addons/webhook/__init__.py
odoo/addons/webhook/__manifest__.py
odoo/addons/webhook/controllers/__init__.py
odoo/addons/webhook/controllers/main.py
odoo/addons/webhook/demo/webhook_demo.xml
odoo/addons/webhook/models/__init__.py
odoo/addons/webhook/models/webhook.py
odoo/addons/webhook/security/ir.model.access.csv
odoo/addons/webhook/tests/__init__.py
odoo/addons/webhook/tests/test_webhook_post.py
odoo/addons/webhook/views/webhook_views.xml
odoo10_addon_webhook-10.0.1.0.0.dist-info/DESCRIPTION.rst
odoo10_addon_webhook-10.0.1.0.0.dist-info/METADATA
odoo10_addon_webhook-10.0.1.0.0.dist-info/RECORD
odoo10_addon_webhook-10.0.1.0.0.dist-info/WHEEL
odoo10_addon_webhook-10.0.1.0.0.dist-info/metadata.json
odoo10_addon_webhook-10.0.1.0.0.dist-info/namespace_packages.txt
odoo10_addon_webhook-10.0.1.0.0.dist-info/top_level.txt
